zipr/azure/__init__.py
zipr/azure/azure.py
zipr_azure-0.0.6.dist-info/METADATA
zipr_azure-0.0.6.dist-info/WHEEL
zipr_azure-0.0.6.dist-info/entry_points.txt
zipr_azure-0.0.6.dist-info/top_level.txt
zipr_azure-0.0.6.dist-info/RECORD
