Metadata-Version: 2.1
Name: zipr-azure
Version: 0.0.6
Summary: UNKNOWN
Home-page: https://github.com/Pointe-Vector/zipr
Author: Andrew Hoekstra
Author-email: andrew@pointevector.com
License: UNKNOWN
Platform: UNKNOWN
Requires-Dist: azure-storage-blob
Requires-Dist: zipr-core
